eu/__init__.py
eu/softfire/MonitoringManager.py
eu/softfire/__init__.py
eu/softfire/exceptions/__init__.py
eu/softfire/exceptions/monitoring/__init__.py
eu/softfire/exceptions/monitoring/exceptions.py
eu/softfire/utils/__init__.py
eu/softfire/utils/monitoring/__init__.py
eu/softfire/utils/monitoring/utils.py
monitoring_manager-0.5.4.data/scripts/monitoring-manager
monitoring_manager-0.5.4.dist-info/DESCRIPTION.rst
monitoring_manager-0.5.4.dist-info/METADATA
monitoring_manager-0.5.4.dist-info/RECORD
monitoring_manager-0.5.4.dist-info/WHEEL
monitoring_manager-0.5.4.dist-info/metadata.json
monitoring_manager-0.5.4.dist-info/top_level.txt
