Metadata-Version: 2.0
Name: monitoring-manager
Version: 0.5.4
Summary: The SoftFIRE Monitoring Manager
Home-page: http://softfire.eu/
Author: SoftFIRE
Author-email: softfire@softfire.eu
License: Apache 2
Keywords: python vnfm nfvo sdk experiment manager softfire tosca openstack rest
Platform: UNKNOWN
Classifier: Development Status :: 4 - Beta
Classifier: Intended Audience :: Developers
Classifier: License :: OSI Approved :: Apache Software License
Requires-Dist: softfire-sdk (==1.1.4)
Requires-Dist: pyyaml
Requires-Dist: python-novaclient (==9.1.1)
Requires-Dist: python-keystoneclient
Requires-Dist: python-neutronclient
Requires-Dist: python-glanceclient
